qiskit_addon_sqd/__init__.py
qiskit_addon_sqd/configuration_recovery.py
qiskit_addon_sqd/counts.py
qiskit_addon_sqd/fermion.py
qiskit_addon_sqd/qubit.py
qiskit_addon_sqd/subsampling.py
qiskit_addon_sqd-0.12.1.dist-info/METADATA
qiskit_addon_sqd-0.12.1.dist-info/WHEEL
qiskit_addon_sqd-0.12.1.dist-info/licenses/LICENSE.txt
qiskit_addon_sqd-0.12.1.dist-info/RECORD
