Metadata-Version: 2.4
Name: qiskit-addon-sqd
Version: 0.12.1
Summary: Classically postprocess noisy quantum samples to yield more accurate energy estimations
License:                     Copyright 2024 IBM and its contributors
License-File: LICENSE.txt
Classifier: Intended Audience :: Developers
Classifier: Intended Audience :: Science/Research
Classifier: License :: OSI Approved :: Apache Software License
Classifier: Natural Language :: English
Classifier: Operating System :: POSIX :: Linux
Classifier: Programming Language :: Python :: 3.10
Classifier: Programming Language :: Python :: 3.11
Classifier: Programming Language :: Python :: 3.12
Classifier: Topic :: Scientific/Engineering :: Physics
Requires-Python: >=3.10
Requires-Dist: jax>=0.4.30
Requires-Dist: jaxlib>=0.4.30
Requires-Dist: numpy>=1.26
Requires-Dist: pyscf>=2.5; sys_platform != 'win32'
Requires-Dist: qiskit<3,>=1.2
Requires-Dist: scipy>=1.13.1
Provides-Extra: basetest
Requires-Dist: pytest-cov>=5.0; extra == 'basetest'
Requires-Dist: pytest>=8.0; extra == 'basetest'
Provides-Extra: dev
Requires-Dist: ffsim; extra == 'dev'
Requires-Dist: jupyter-sphinx; extra == 'dev'
Requires-Dist: matplotlib; extra == 'dev'
Requires-Dist: mypy==1.19.1; extra == 'dev'
Requires-Dist: nbmake>=1.5.0; extra == 'dev'
Requires-Dist: nbqa>=1.8.5; extra == 'dev'
Requires-Dist: nbsphinx>=0.9.4; extra == 'dev'
Requires-Dist: pylatexenc; extra == 'dev'
Requires-Dist: pylint==4.0.4; extra == 'dev'
Requires-Dist: pytest-cov>=5.0; extra == 'dev'
Requires-Dist: pytest>=8.0; extra == 'dev'
Requires-Dist: qiskit; extra == 'dev'
Requires-Dist: qiskit-addon-utils; extra == 'dev'
Requires-Dist: qiskit-aer; extra == 'dev'
Requires-Dist: qiskit-ibm-runtime; extra == 'dev'
Requires-Dist: qiskit-sphinx-theme~=2.0.0; extra == 'dev'
Requires-Dist: reno>=4.1; extra == 'dev'
Requires-Dist: ruff==0.12.11; extra == 'dev'
Requires-Dist: sphinx-autodoc-typehints; extra == 'dev'
Requires-Dist: sphinx-copybutton; extra == 'dev'
Requires-Dist: sphinx-design; extra == 'dev'
Requires-Dist: sphinx-reredirects; extra == 'dev'
Requires-Dist: toml>=0.9.6; extra == 'dev'
Requires-Dist: tox>=4.4.3; extra == 'dev'
Provides-Extra: docs
Requires-Dist: ffsim; extra == 'docs'
Requires-Dist: jupyter-sphinx; extra == 'docs'
Requires-Dist: matplotlib; extra == 'docs'
Requires-Dist: nbsphinx>=0.9.4; extra == 'docs'
Requires-Dist: pylatexenc; extra == 'docs'
Requires-Dist: pytest-cov>=5.0; extra == 'docs'
Requires-Dist: pytest>=8.0; extra == 'docs'
Requires-Dist: qiskit; extra == 'docs'
Requires-Dist: qiskit-addon-utils; extra == 'docs'
Requires-Dist: qiskit-aer; extra == 'docs'
Requires-Dist: qiskit-ibm-runtime; extra == 'docs'
Requires-Dist: qiskit-sphinx-theme~=2.0.0; extra == 'docs'
Requires-Dist: reno>=4.1; extra == 'docs'
Requires-Dist: sphinx-autodoc-typehints; extra == 'docs'
Requires-Dist: sphinx-copybutton; extra == 'docs'
Requires-Dist: sphinx-design; extra == 'docs'
Requires-Dist: sphinx-reredirects; extra == 'docs'
Provides-Extra: lint
Requires-Dist: mypy==1.19.1; extra == 'lint'
Requires-Dist: nbqa>=1.8.5; extra == 'lint'
Requires-Dist: pylint==4.0.4; extra == 'lint'
Requires-Dist: reno>=4.1; extra == 'lint'
Requires-Dist: ruff==0.12.11; extra == 'lint'
Requires-Dist: toml>=0.9.6; extra == 'lint'
Provides-Extra: nbtest
Requires-Dist: nbmake>=1.5.0; extra == 'nbtest'
Requires-Dist: pytest-cov>=5.0; extra == 'nbtest'
Requires-Dist: pytest>=8.0; extra == 'nbtest'
Provides-Extra: notebook-dependencies
Requires-Dist: ffsim; extra == 'notebook-dependencies'
Requires-Dist: matplotlib; extra == 'notebook-dependencies'
Requires-Dist: pylatexenc; extra == 'notebook-dependencies'
Requires-Dist: qiskit; extra == 'notebook-dependencies'
Requires-Dist: qiskit-addon-utils; extra == 'notebook-dependencies'
Requires-Dist: qiskit-aer; extra == 'notebook-dependencies'
Requires-Dist: qiskit-ibm-runtime; extra == 'notebook-dependencies'
Provides-Extra: style
Requires-Dist: nbqa>=1.8.5; extra == 'style'
Requires-Dist: ruff==0.12.11; extra == 'style'
Provides-Extra: test
Requires-Dist: pytest-cov>=5.0; extra == 'test'
Requires-Dist: pytest>=8.0; extra == 'test'
